PRINT/PRINT.py
PRINT/__init__.py
mino_print-0.1.0.dist-info/LICENSE
mino_print-0.1.0.dist-info/METADATA
mino_print-0.1.0.dist-info/WHEEL
mino_print-0.1.0.dist-info/RECORD
