Metadata-Version: 2.1
Name: mino-print
Version: 0.1.0
Summary: PRINT
License: MIT
Author: minoru
Author-email: gabrielikenaga@gmail.com
Requires-Python: >=3.10,<4.0
Classifier: License :: OSI Approved :: MIT License
Classifier: Programming Language :: Python :: 3
Classifier: Programming Language :: Python :: 3.10
Classifier: Programming Language :: Python :: 3.11
Classifier: Programming Language :: Python :: 3.12
Requires-Dist: colorama (>=0.4.6,<0.5.0)
Requires-Dist: pyfiglet (>=1.0.2,<2.0.0)
